k8s_job_scheduler/__init__.py
k8s_job_scheduler/job_manager.py
k8s_job_scheduler/python_executor.py
k8s_job_scheduler-0.2.3.dist-info/LICENSE.txt
k8s_job_scheduler-0.2.3.dist-info/METADATA
k8s_job_scheduler-0.2.3.dist-info/WHEEL
k8s_job_scheduler-0.2.3.dist-info/top_level.txt
k8s_job_scheduler-0.2.3.dist-info/RECORD
