Metadata-Version: 2.1
Name: k8s-job-scheduler
Version: 0.2.3
Summary: Kubernetes job scheduler for Python
Home-page: https://github.com/pyscaffold/pyscaffold/
Author: Meir Tseitlin
Author-email: opensource@imubit.com
License: LGPLv3
Project-URL: Documentation, https://github.com/imubit/k8s-job-scheduler/
Project-URL: Source, https://github.com/imubit/k8s-job-scheduler
Platform: any
Classifier: Development Status :: 4 - Beta
Classifier: Programming Language :: Python
License-File: LICENSE.txt
Requires-Dist: kubernetes
Requires-Dist: dill
Requires-Dist: importlib-metadata ; python_version < "3.8"
Provides-Extra: testing
Requires-Dist: setuptools ; extra == 'testing'
Requires-Dist: pytest ; extra == 'testing'
Requires-Dist: pytest-cov ; extra == 'testing'
